pip_setuptools/__init__.py
pip_setuptools/package_compiler.py
pip_setuptools-1.1.4.dist-info/METADATA
pip_setuptools-1.1.4.dist-info/WHEEL
pip_setuptools-1.1.4.dist-info/entry_points.txt
pip_setuptools-1.1.4.dist-info/top_level.txt
pip_setuptools-1.1.4.dist-info/RECORD
